aws_solutions_constructs/aws_cloudfront_mediastore/__init__.py
aws_solutions_constructs/aws_cloudfront_mediastore/py.typed
aws_solutions_constructs/aws_cloudfront_mediastore/_jsii/__init__.py
aws_solutions_constructs/aws_cloudfront_mediastore/_jsii/aws-cloudfront-mediastore@2.94.0.jsii.tgz
aws_solutions_constructs_aws_cloudfront_mediastore-2.94.0.dist-info/LICENSE
aws_solutions_constructs_aws_cloudfront_mediastore-2.94.0.dist-info/METADATA
aws_solutions_constructs_aws_cloudfront_mediastore-2.94.0.dist-info/WHEEL
aws_solutions_constructs_aws_cloudfront_mediastore-2.94.0.dist-info/top_level.txt
aws_solutions_constructs_aws_cloudfront_mediastore-2.94.0.dist-info/RECORD
