Metadata-Version: 2.1
Name: aws-solutions-constructs.aws-cloudfront-mediastore
Version: 2.94.0
Summary: CDK Constructs for Amazon CloudFront to AWS Elemental MediaStore integration.
Home-page: https://github.com/awslabs/aws-solutions-constructs.git
Author: Amazon Web Services
License: Apache-2.0
Project-URL: Source, https://github.com/awslabs/aws-solutions-constructs.git
Classifier: Intended Audience :: Developers
Classifier: Operating System :: OS Independent
Classifier: Programming Language :: JavaScript
Classifier: Programming Language :: Python :: 3 :: Only
Classifier: Programming Language :: Python :: 3.9
Classifier: Programming Language :: Python :: 3.10
Classifier: Programming Language :: Python :: 3.11
Classifier: Typing :: Typed
Classifier: License :: OSI Approved
Requires-Python: ~=3.9
License-File: LICENSE
Requires-Dist: aws-cdk-lib <3.0.0,>=2.219.0
Requires-Dist: aws-solutions-constructs.core ==2.94.0
Requires-Dist: constructs <11.0.0,>=10.0.0
Requires-Dist: jsii <2.0.0,>=1.114.1
Requires-Dist: publication >=0.0.3
Requires-Dist: typeguard <4.3.0,>=2.13.3
